oxipng/__init__.py
oxipng/__init__.pyi
oxipng/oxipng.cpython-310-aarch64-linux-gnu.so
oxipng/py.typed
pyoxipng-9.1.1.dist-info/METADATA
pyoxipng-9.1.1.dist-info/WHEEL
pyoxipng-9.1.1.dist-info/licenses/LICENSE
pyoxipng-9.1.1.dist-info/RECORD
