Metadata-Version: 2.4
Name: pyoxipng
Version: 9.1.1
Classifier: License :: OSI Approved :: MIT License
Classifier: Programming Language :: Rust
Classifier: Programming Language :: Python :: Implementation :: CPython
Classifier: Programming Language :: Python :: Implementation :: PyPy
Classifier: Topic :: Utilities
License-File: LICENSE
Summary: Python wrapper for multithreaded .png image file optimizer oxipng
Keywords: rust,image,optimize,optimizer,optimization,compress,png
Author: Nick Frasser <nfrasser@users.noreply.github.com>
Requires-Python: >=3.8
Project-URL: homepage, https://github.com/nfrasser/pyoxipng
Project-URL: documentation, https://github.com/nfrasser/pyoxipng#readme
Project-URL: repository, https://github.com/nfrasser/pyoxipng
Project-URL: changelog, https://github.com/nfrasser/pyoxipng/blob/main/CHANGELOG.md
